config_converter/__init__.py
config_converter/converter.py
config_converter/main.py
universal_config_converter-0.2.0.dist-info/licenses/LICENSE
universal_config_converter-0.2.0.dist-info/METADATA
universal_config_converter-0.2.0.dist-info/WHEEL
universal_config_converter-0.2.0.dist-info/entry_points.txt
universal_config_converter-0.2.0.dist-info/top_level.txt
universal_config_converter-0.2.0.dist-info/RECORD
