Metadata-Version: 2.4
Name: universal-config-converter
Version: 0.2.0
Summary: A command-line tool to convert between various configuration file formats (JSON, YAML, TOML, .env, INI, XML).
Author-email: velibenek <velibenek@gmail.com>
Project-URL: Homepage, https://github.com/velibenek/universal-config-converter
Project-URL: Issues, https://github.com/velibenek/universal-config-converter/issues
Classifier: Programming Language :: Python :: 3
Classifier: License :: OSI Approved :: MIT License
Classifier: Operating System :: OS Independent
Classifier: Topic :: Utilities
Classifier: Environment :: Console
Classifier: Intended Audience :: Developers
Classifier: Topic :: Software Development :: Libraries :: Python Modules
Requires-Python: >=3.8
License-File: LICENSE
Requires-Dist: pyyaml>=6.0
Requires-Dist: ruamel.yaml>=0.17.0
Requires-Dist: tomlkit>=0.12.0
Requires-Dist: python-dotenv>=1.0.0
Requires-Dist: click>=8.0
Requires-Dist: xmltodict>=0.13.0
Requires-Dist: jsonschema>=4.0.0
Dynamic: license-file
